{
    "type": "FeatureCollection",
    "features": [
        {
            "type": "Feature",
            "id": "33661011",
            "properties": {
                "name": "广丰县",
                "cp": [
                    118.2030878871,
                    28.4382835647
                ],
                "childNum": 11
            },
            "geometry": {
                "type": "MultiPolygon",
                "coordinates": [
                    [
                        [
                            [
                                118.107345,
                                28.5738430000001
                            ],
                            [
                                118.103922148438,
                                28.5616506171876
                            ],
                            [
                                118.095152617188,
                                28.5704201484375
                            ],
                            [
                                118.107345,
                                28.5738430000001
                            ]
                        ]
                    ],
                    [
                        [
                            [
                                118.107345,
                                28.5738430000001
                            ],
                            [
                                118.110704375,
                                28.580483625
                            ],
                            [
                                118.13287234375,
                                28.5916994453125
                            ],
                            [
                                118.137345,
                                28.6138430000001
                            ],
                            [
                                118.16877078125,
                                28.606704328125
                            ],
                            [
                                118.224928007813,
                                28.6282888007812
                            ],
                            [
                                118.232984648438,
                                28.5889772773438
                            ],
                            [
                                118.231666289063,
                                28.5783669257813
                            ],
                            [
                                118.26677859375,
                                28.5570412421876
                            ],
                            [
                                118.28834109375,
                                28.5301125312501
                            ],
                            [
                                118.317867460938,
                                28.5669850898438
                            ],
                            [
                                118.33357546875,
                                28.5120583320312
                            ],
                            [
                                118.382589140625,
                                28.49806175
                            ],
                            [
                                118.417345,
                                28.523843
                            ],
                            [
                                118.441612578125,
                                28.5172634101563
                            ],
                            [
                                118.433077421875,
                                28.5081081367188
                            ],
                            [
                                118.40966921875,
                                28.4988063789063
                            ],
                            [
                                118.47127078125,
                                28.4766286445313
                            ],
                            [
                                118.43865359375,
                                28.4028884101563
                            ],
                            [
                                118.468863554688,
                                28.3540773750001
                            ],
                            [
                                118.47443484375,
                                28.3217018867188
                            ],
                            [
                                118.443077421875,
                                28.2981081367187
                            ],
                            [
                                118.427345,
                                28.293843
                            ],
                            [
                                118.411793242188,
                                28.2893971992188
                            ],
                            [
                                118.392896757813,
                                28.2782888007813
                            ],
                            [
                                118.371793242188,
                                28.2693971992188
                            ],
                            [
                                118.320533476563,
                                28.2284011054688
                            ],
                            [
                                118.323311796875,
                                28.2060768867188
                            ],
                            [
                                118.362896757813,
                                28.1893971992188
                            ],
                            [
                                118.377100859375,
                                28.1716579414063
                            ],
                            [
                                118.361793242188,
                                28.1593971992188
                            ],
                            [
                                118.34884890625,
                                28.0995778632813
                            ],
                            [
                                118.269801054688,
                                28.0824733710938
                            ],
                            [
                                118.247345,
                                28.0738430000001
                            ],
                            [
                                118.230704375,
                                28.070483625
                            ],
                            [
                                118.217345,
                                28.063843
                            ],
                            [
                                118.21271609375,
                                28.07921409375
                            ],
                            [
                                118.201163359375,
                                28.0891677070313
                            ],
                            [
                                118.203472929688,
                                28.1178615546876
                            ],
                            [
                                118.19197390625,
                                28.1384719062501
                            ],
                            [
                                118.178277617188,
                                28.1691579414063
                            ],
                            [
                                118.1965246875,
                                28.218843
                            ],
                            [
                                118.17295046875,
                                28.28304221875
                            ],
                            [
                                118.196944609375,
                                28.3260500312501
                            ],
                            [
                                118.124576445313,
                                28.3062429023438
                            ],
                            [
                                118.06271609375,
                                28.3592140937501
                            ],
                            [
                                118.03197390625,
                                28.37847190625
                            ],
                            [
                                118.027345,
                                28.393843
                            ],
                            [
                                118.04298953125,
                                28.3981984687501
                            ],
                            [
                                118.051754179688,
                                28.4296706367188
                            ],
                            [
                                118.067345,
                                28.4273659492188
                            ],
                            [
                                118.082345,
                                28.4295827460938
                            ],
                            [
                                118.092735625,
                                28.4280471015625
                            ],
                            [
                                118.129796171875,
                                28.4504030585938
                            ],
                            [
                                118.153741484375,
                                28.5089064765625
                            ],
                            [
                                118.14170046875,
                                28.51819846875
                            ],
                            [
                                118.132955351563,
                                28.5696730781251
                            ],
                            [
                                118.12205203125,
                                28.56806175
                            ],
                            [
                                118.107345,
                                28.5738430000001
                            ]
                        ]
                    ]
                ]

            }
        }
    ]
}